torchglyph/__init__.py
torchglyph/__main__.py
torchglyph/dataset.py
torchglyph/hooks.py
torchglyph/io.py
torchglyph/meter.py
torchglyph/optimizer.py
torchglyph/sampler.py
torchglyph/scheduler.py
torchglyph/vocab.py
torchglyph/datasets/__init__.py
torchglyph/datasets/machine_translation.py
torchglyph/datasets/named_entity_recognition.py
torchglyph/formats/__init__.py
torchglyph/formats/conll.py
torchglyph/formats/freq.py
torchglyph/formats/primitive.py
torchglyph/formats/vector.py
torchglyph/nn/__init__.py
torchglyph/nn/activation.py
torchglyph/nn/attention.py
torchglyph/nn/embedding.py
torchglyph/nn/init.py
torchglyph/nn/linear.py
torchglyph/nn/transformer.py
torchglyph/pipe/__init__.py
torchglyph/pipe/abc.py
torchglyph/pipe/catting.py
torchglyph/pipe/packing.py
torchglyph/pipe/padding.py
torchglyph/proc/__init__.py
torchglyph/proc/abc.py
torchglyph/proc/basic.py
torchglyph/proc/catting.py
torchglyph/proc/collating.py
torchglyph/proc/mlm.py
torchglyph/proc/packing.py
torchglyph/proc/padding.py
torchglyph/proc/vocab.py
torchglyph-0.3.2.dist-info/LICENSE
torchglyph-0.3.2.dist-info/METADATA
torchglyph-0.3.2.dist-info/WHEEL
torchglyph-0.3.2.dist-info/top_level.txt
torchglyph-0.3.2.dist-info/RECORD
