Metadata-Version: 2.1
Name: torchglyph
Version: 0.3.2
Summary: Data Processor Combinators for Natural Language Processing
Home-page: https://speedcell4.github.io/torchglyph
Author: speedcell4
Author-email: speedcell4@gmail.com
License: MIT
Platform: UNKNOWN
Requires-Dist: tqdm
Requires-Dist: numpy
Requires-Dist: einops
Requires-Dist: torchrua (>=0.4.0)
Requires-Dist: requests
Requires-Dist: tabulate
Requires-Dist: aku
Provides-Extra: ctx
Requires-Dist: transformers ; extra == 'ctx'
Provides-Extra: dev
Requires-Dist: pytest ; extra == 'dev'
Requires-Dist: hypothesis ; extra == 'dev'
Provides-Extra: docs
Requires-Dist: mkdocs ; extra == 'docs'
Requires-Dist: mkdocs-alabaster ; extra == 'docs'
